<?xml version="1.0" encoding="utf-8" standalone="yes"?>
<Gesture Name = "Circle">
	<Stroke>
		<Point X = "2,104228" Y = "1,67642" T = "0" Pressure = "0" />
		<Point X = "2,094426" Y = "1,680263" T = "0" Pressure = "0" />
		<Point X = "2,085871" Y = "1,689172" T = "0" Pressure = "0" />
		<Point X = "2,079023" Y = "1,696635" T = "0" Pressure = "0" />
		<Point X = "2,072939" Y = "1,705743" T = "0" Pressure = "0" />
		<Point X = "2,064762" Y = "1,713762" T = "0" Pressure = "0" />
		<Point X = "2,056187" Y = "1,720845" T = "0" Pressure = "0" />
		<Point X = "2,04283" Y = "1,73228" T = "0" Pressure = "0" />
		<Point X = "2,029999" Y = "1,743756" T = "0" Pressure = "0" />
		<Point X = "2,018819" Y = "1,753088" T = "0" Pressure = "0" />
		<Point X = "2,007689" Y = "1,75901" T = "0" Pressure = "0" />
		<Point X = "1,996156" Y = "1,761739" T = "0" Pressure = "0" />
		<Point X = "1,985275" Y = "1,766261" T = "0" Pressure = "0" />
		<Point X = "1,97541" Y = "1,771285" T = "0" Pressure = "0" />
		<Point X = "1,960564" Y = "1,777034" T = "0" Pressure = "0" />
		<Point X = "1,947741" Y = "1,781968" T = "0" Pressure = "0" />
		<Point X = "1,931336" Y = "1,783154" T = "0" Pressure = "0" />
		<Point X = "1,916743" Y = "1,781181" T = "0" Pressure = "0" />
		<Point X = "1,903151" Y = "1,777392" T = "0" Pressure = "0" />
		<Point X = "1,889897" Y = "1,776791" T = "0" Pressure = "0" />
		<Point X = "1,876645" Y = "1,774245" T = "0" Pressure = "0" />
		<Point X = "1,865616" Y = "1,772233" T = "0" Pressure = "0" />
		<Point X = "1,855443" Y = "1,767414" T = "0" Pressure = "0" />
		<Point X = "1,848305" Y = "1,757703" T = "0" Pressure = "0" />
		<Point X = "1,840667" Y = "1,748777" T = "0" Pressure = "0" />
		<Point X = "1,838053" Y = "1,735132" T = "0" Pressure = "0" />
		<Point X = "1,831424" Y = "1,726005" T = "0" Pressure = "0" />
		<Point X = "1,832914" Y = "1,710039" T = "0" Pressure = "0" />
		<Point X = "1,831833" Y = "1,700163" T = "0" Pressure = "0" />
		<Point X = "1,828965" Y = "1,687689" T = "0" Pressure = "0" />
		<Point X = "1,824959" Y = "1,677548" T = "0" Pressure = "0" />
		<Point X = "1,82797" Y = "1,665389" T = "0" Pressure = "0" />
		<Point X = "1,827725" Y = "1,653783" T = "0" Pressure = "0" />
		<Point X = "1,824809" Y = "1,643299" T = "0" Pressure = "0" />
		<Point X = "1,822451" Y = "1,633553" T = "0" Pressure = "0" />
		<Point X = "1,819546" Y = "1,620653" T = "0" Pressure = "0" />
		<Point X = "1,817052" Y = "1,605697" T = "0" Pressure = "0" />
		<Point X = "1,814413" Y = "1,592003" T = "0" Pressure = "0" />
		<Point X = "1,815786" Y = "1,579129" T = "0" Pressure = "0" />
		<Point X = "1,821209" Y = "1,55765" T = "0" Pressure = "0" />
		<Point X = "1,824927" Y = "1,54033" T = "0" Pressure = "0" />
		<Point X = "1,829072" Y = "1,523924" T = "0" Pressure = "0" />
		<Point X = "1,833977" Y = "1,513053" T = "0" Pressure = "0" />
		<Point X = "1,837" Y = "1,502093" T = "0" Pressure = "0" />
		<Point X = "1,846764" Y = "1,501745" T = "0" Pressure = "0" />
		<Point X = "1,857464" Y = "1,49536" T = "0" Pressure = "0" />
		<Point X = "1,870049" Y = "1,488208" T = "0" Pressure = "0" />
		<Point X = "1,882467" Y = "1,485032" T = "0" Pressure = "0" />
		<Point X = "1,895078" Y = "1,484037" T = "0" Pressure = "0" />
		<Point X = "1,904754" Y = "1,486836" T = "0" Pressure = "0" />
		<Point X = "1,916026" Y = "1,492825" T = "0" Pressure = "0" />
		<Point X = "1,926569" Y = "1,496547" T = "0" Pressure = "0" />
		<Point X = "1,938284" Y = "1,499551" T = "0" Pressure = "0" />
		<Point X = "1,952103" Y = "1,501287" T = "0" Pressure = "0" />
		<Point X = "1,964562" Y = "1,5018" T = "0" Pressure = "0" />
		<Point X = "1,977504" Y = "1,503919" T = "0" Pressure = "0" />
		<Point X = "1,989981" Y = "1,506595" T = "0" Pressure = "0" />
		<Point X = "2,001186" Y = "1,508579" T = "0" Pressure = "0" />
		<Point X = "2,011673" Y = "1,509317" T = "0" Pressure = "0" />
		<Point X = "2,024169" Y = "1,514795" T = "0" Pressure = "0" />
		<Point X = "2,034592" Y = "1,520282" T = "0" Pressure = "0" />
		<Point X = "2,037937" Y = "1,528506" T = "0" Pressure = "0" />
		<Point X = "2,038168" Y = "1,539155" T = "0" Pressure = "0" />
		<Point X = "2,041732" Y = "1,550584" T = "0" Pressure = "0" />
		<Point X = "2,048853" Y = "1,559598" T = "0" Pressure = "0" />
		<Point X = "2,058181" Y = "1,569162" T = "0" Pressure = "0" />
		<Point X = "2,062047" Y = "1,579055" T = "0" Pressure = "0" />
		<Point X = "2,063786" Y = "1,587859" T = "0" Pressure = "0" />
		<Point X = "2,070526" Y = "1,598734" T = "0" Pressure = "0" />
		<Point X = "2,077422" Y = "1,605652" T = "0" Pressure = "0" />
		<Point X = "2,086893" Y = "1,613207" T = "0" Pressure = "0" />
		<Point X = "2,093156" Y = "1,623368" T = "0" Pressure = "0" />
		<Point X = "2,092315" Y = "1,635994" T = "0" Pressure = "0" />
		<Point X = "2,092307" Y = "1,647615" T = "0" Pressure = "0" />
		<Point X = "2,089049" Y = "1,657799" T = "0" Pressure = "0" />
		<Point X = "2,086491" Y = "1,669036" T = "0" Pressure = "0" />
		<Point X = "2,086125" Y = "1,678894" T = "0" Pressure = "0" />
		<Point X = "2,078663" Y = "1,684167" T = "0" Pressure = "0" />
	</Stroke>
</Gesture>
